mizue/__init__.py
mizue/file/__init__.py
mizue/file/fileutils.py
mizue/network/__init__.py
mizue/network/downloader/__init__.py
mizue/network/downloader/download_event.py
mizue/network/downloader/download_metadata.py
mizue/network/downloader/downloader.py
mizue/network/downloader/downloader_tool.py
mizue/network/downloader/progress_data.py
mizue/network/downloader/data/colors.json
mizue/printer/__init__.py
mizue/printer/colorizer.py
mizue/printer/printer.py
mizue/printer/terminal_colors.py
mizue/printer/grid/__init__.py
mizue/printer/grid/alignment.py
mizue/printer/grid/border_character_codes.py
mizue/printer/grid/border_style.py
mizue/printer/grid/cell_renderer_args.py
mizue/printer/grid/column.py
mizue/printer/grid/column_settings.py
mizue/printer/grid/grid.py
mizue/printer/grid/row_border_position.py
mizue/progress/__init__.py
mizue/progress/colorful_progress.py
mizue/progress/progress.py
mizue/progress/progress_renderer_args.py
mizue/progress/spinner.py
mizue/util/__init__.py
mizue/util/event_listener.py
mizue/util/signal_handler.py
mizue/util/stoppable_thread.py
mizue/util/utility.py
mizue-0.7.4.dist-info/LICENSE
mizue-0.7.4.dist-info/METADATA
mizue-0.7.4.dist-info/WHEEL
mizue-0.7.4.dist-info/top_level.txt
mizue-0.7.4.dist-info/RECORD
