Metadata-Version: 2.1
Name: mizue
Version: 0.7.4
Summary: A Python package for various utilities
Author: Hoshilily
License: MIT
Classifier: Intended Audience :: Developers
Classifier: License :: OSI Approved :: MIT License
Classifier: Programming Language :: Python :: 3
License-File: LICENSE
Requires-Dist: wcwidth
